agenticagi/__init__.py
agenticagi/agi_wrapper.py
AgenticAGI-0.1.3.dist-info/LICENSE
AgenticAGI-0.1.3.dist-info/METADATA
AgenticAGI-0.1.3.dist-info/WHEEL
AgenticAGI-0.1.3.dist-info/top_level.txt
AgenticAGI-0.1.3.dist-info/RECORD
