Metadata-Version: 2.1
Name: AgenticAGI
Version: 0.1.3
Summary: Python wrapper for AGI executable
Home-page: https://github.com/simulanics/AgenticAGI
Author: Simulanics Technologies
Author-email: mcombatti@simulanics.org
Classifier: Programming Language :: Python :: 3
Classifier: Operating System :: OS Independent
Requires-Python: >=3.6
License-File: LICENSE
